clouddatabridge/__init__.py
clouddatabridge/aws_db.py
clouddatabridge/azure_db.py
clouddatabridge/db_connection.py
clouddatabridge/db_manager.py
clouddatabridge/gcp_db.py
clouddatabridge/local_db.py
clouddatabridge/rds_execute.py
clouddatabridge-0.1.40.dist-info/LICENSE
clouddatabridge-0.1.40.dist-info/METADATA
clouddatabridge-0.1.40.dist-info/WHEEL
clouddatabridge-0.1.40.dist-info/top_level.txt
clouddatabridge-0.1.40.dist-info/RECORD
